flask_redisconfig
