Metadata-Version: 1.0
Name: Flask-RedisConfig
Version: 0.1.0
Summary: Redis-backed config for Flask applications
Home-page: https://github.com/marksteve/flask-redisconfig
Author: Mark Steve Samson
Author-email: hello@marksteve.com
License: MIT
Platform: any
